AUTHORS.rst
CONTRIBUTING.rst
HISTORY.rst
LICENSE
MANIFEST.in
README.rst
setup.cfg
setup.py
ipgetter2/__init__.py
ipgetter2/__main__.py
ipgetter2/compatible.py
ipgetter2/exceptions.py
ipgetter2/ipgetter1.py
ipgetter2/ipgetter2.py
ipgetter2.egg-info/PKG-INFO
ipgetter2.egg-info/SOURCES.txt
ipgetter2.egg-info/dependency_links.txt
ipgetter2.egg-info/entry_points.txt
ipgetter2.egg-info/not-zip-safe
ipgetter2.egg-info/requires.txt
ipgetter2.egg-info/top_level.txt
tests/__init__.py
tests/test_compatible.py
tests/test_console.py
tests/test_ipgetter1.py
tests/test_ipgetter2.py